<annotation>
	<folder/>
	<filename>quandoi102.jpg</filename>
	<path>.\data\/quandoi102.jpg</path>
	<source>
		<database>Unknown</database>
	</source>
	<size>
		<width>620</width>
		<height>349</height>
		<depth>3</depth>
	</size>
	<segmented>0</segmented>
	<object>
		<name>plate</name>
		<pose>Unspecified</pose>
		<truncated>0</truncated>
		<difficult>0</difficult>
		<bndbox>
			<xmin>498</xmin>
			<ymin>223</ymin>
			<xmax>524</xmax>
			<ymax>245</ymax>
		</bndbox>
	</object>
	<object>
		<name>plate</name>
		<pose>Unspecified</pose>
		<truncated>0</truncated>
		<difficult>0</difficult>
		<bndbox>
			<xmin>62</xmin>
			<ymin>238</ymin>
			<xmax>81</xmax>
			<ymax>245</ymax>
		</bndbox>
	</object>
</annotation>
